redrawing/__init__.py
redrawing/test_client.py
redrawing/ai_models/LightweightOpenPose.py
redrawing/ai_models/OAK_blazepose.py
redrawing/ai_models/OAK_hand_pose.py
redrawing/ai_models/OAK_human_pose.py
redrawing/ai_models/__init__.py
redrawing/ai_models/third_models/__init__.py
redrawing/ai_models/third_models/lightweight_human/LICENSE
redrawing/ai_models/third_models/lightweight_human/__init__.py
redrawing/ai_models/third_models/lightweight_human/conv.py
redrawing/ai_models/third_models/lightweight_human/get_parameters.py
redrawing/ai_models/third_models/lightweight_human/image_tools.py
redrawing/ai_models/third_models/lightweight_human/keypoints.py
redrawing/ai_models/third_models/lightweight_human/load_state.py
redrawing/ai_models/third_models/lightweight_human/loss.py
redrawing/ai_models/third_models/lightweight_human/one_euro_filter.py
redrawing/ai_models/third_models/lightweight_human/openpose_light.pth
redrawing/ai_models/third_models/lightweight_human/pose.py
redrawing/ai_models/third_models/lightweight_human/models/__init__.py
redrawing/ai_models/third_models/lightweight_human/models/with_mobilenet.py
redrawing/ai_models/third_models/oak_blazepose/BlazeposeDepthai.py
redrawing/ai_models/third_models/oak_blazepose/FPS.py
redrawing/ai_models/third_models/oak_blazepose/LICENSE
redrawing/ai_models/third_models/oak_blazepose/__init__.py
redrawing/ai_models/third_models/oak_blazepose/blazepose_pose_detection.blob
redrawing/ai_models/third_models/oak_blazepose/blazepose_pose_landmark_full_body.blob
redrawing/ai_models/third_models/oak_blazepose/blazepose_pose_landmark_upper_body.blob
redrawing/ai_models/third_models/oak_blazepose/mediapipe_utils.py
redrawing/ai_models/third_models/oak_blazepose/o3d_utils.py
redrawing/ai_models/third_models/oak_hand_tracker/FPS.py
redrawing/ai_models/third_models/oak_hand_tracker/HandTracker.py
redrawing/ai_models/third_models/oak_hand_tracker/LICENSE
redrawing/ai_models/third_models/oak_hand_tracker/__init__.py
redrawing-1.0.3.dist-info/LICENSE.md
redrawing-1.0.3.dist-info/METADATA
redrawing-1.0.3.dist-info/WHEEL
redrawing-1.0.3.dist-info/top_level.txt
redrawing-1.0.3.dist-info/RECORD
