Metadata-Version: 2.1
Name: redrawing
Version: 1.0.3
Summary: Python package provinding tools for artistic interactive applications using AI
Home-page: https://github.com/ReDrawing/redrawing
Author: ReDrawing Campinas
Author-email: redrawing.campinas@cti.gov.br
License: MIT License
Project-URL: Bug Tracker, https://github.com/ReDrawing/redrawing/issues
Project-URL: Documentation, https://redrawing.github.io/docs/
Platform: UNKNOWN
Classifier: Programming Language :: Python :: 3
Classifier: License :: OSI Approved :: MIT License
Classifier: Operating System :: OS Independent
Classifier: Topic :: Artistic Software
Classifier: Topic :: Scientific/Engineering :: Artificial Intelligence
Classifier: License :: OSI Approved :: MIT License
Requires-Python: >=3.6
Requires-Dist: numpy
Requires-Dist: scipy
Requires-Dist: matplotlib
Requires-Dist: opencv-python
Requires-Dist: depthai (>=2.9.0)
Requires-Dist: open3d
Provides-Extra: lightweightopenpose
Requires-Dist: torch ; extra == 'lightweightopenpose'
